MANIFEST.in
README.txt
setup.cfg
setup.py
docs/HISTORY.txt
docs/INSTALL.txt
docs/LICENSE.txt
jalon/__init__.py
jalon.policy.egg-info/PKG-INFO
jalon.policy.egg-info/SOURCES.txt
jalon.policy.egg-info/dependency_links.txt
jalon.policy.egg-info/entry_points.txt
jalon.policy.egg-info/namespace_packages.txt
jalon.policy.egg-info/not-zip-safe
jalon.policy.egg-info/paster_plugins.txt
jalon.policy.egg-info/requires.txt
jalon.policy.egg-info/top_level.txt
jalon/policy/__init__.py
jalon/policy/configure.zcml
jalon/policy/setuphandlers.py
jalon/policy/tests.py
jalon/policy/profiles/default/jalon.policy-install.txt
jalon/policy/profiles/default/jalon.policy-various.txt
jalon/policy/profiles/default/metadata.xml
jalon/policy/profiles/default/portlets.xml
jalon/policy/profiles/default/rolemap.xml
jalon/policy/profiles/default/structure/.objects
jalon/policy/profiles/default/structure/.properties
jalon/policy/profiles/default/structure/front-page
jalon/policy/profiles/default/structure/acl_users/.objects
jalon/policy/profiles/default/structure/acl_users/borg_localroles.xml
jalon/policy/profiles/default/structure/acl_users/chooser.xml
jalon/policy/profiles/default/structure/acl_users/credentials_basic_auth.xml
jalon/policy/profiles/default/structure/acl_users/credentials_cookie_auth.xml
jalon/policy/profiles/default/structure/acl_users/ldap-plugin-etu.xml
jalon/policy/profiles/default/structure/acl_users/ldap-plugin.xml
jalon/policy/profiles/default/structure/acl_users/local_roles.xml
jalon/policy/profiles/default/structure/acl_users/mutable_properties.xml
jalon/policy/profiles/default/structure/acl_users/pluginregistry.xml
jalon/policy/profiles/default/structure/acl_users/portal_role_manager.xml
jalon/policy/profiles/default/structure/acl_users/recursive_groups.xml
jalon/policy/profiles/default/structure/acl_users/sniffer.xml
jalon/policy/profiles/default/structure/acl_users/source_groups.xml
jalon/policy/profiles/default/structure/acl_users/source_users.xml
jalon/policy/profiles/default/structure/acl_users/user_factory.xml
jalon/policy/profiles/default/structure/cours/.objects
jalon/policy/profiles/default/structure/cours/.properties
jalon/policy/profiles/default/structure/etudiants/.objects
jalon/policy/profiles/default/structure/etudiants/.properties
jalon/policy/profiles/default/structure/public/.objects
