Metadata-Version: 1.1
Name: jalon.policy
Version: 2.2.4
Summary: Configuration de jalon
Home-page: http://unice.fr
Author: Bordonado Christophe - Université Nice Sophia Antipolis (uns) Service TICE
Author-email: tice@unice.fr
License: CECILL
Platform: UNKNOWN
Classifier: Framework :: Plone
Classifier: Programming Language :: Python
